LICENSE
README.md
setup.py
HiveNetSimpleFlask/__init__.py
HiveNetSimpleFlask/auth.py
HiveNetSimpleFlask/client.py
HiveNetSimpleFlask/server.py
HiveNetSimpleFlask.egg-info/PKG-INFO
HiveNetSimpleFlask.egg-info/SOURCES.txt
HiveNetSimpleFlask.egg-info/dependency_links.txt
HiveNetSimpleFlask.egg-info/not-zip-safe
HiveNetSimpleFlask.egg-info/requires.txt
HiveNetSimpleFlask.egg-info/top_level.txt