Metadata-Version: 2.1
Name: HiveNetSimpleFlask
Version: 0.1.0
Summary: Simplifies the complexity of building restful API based on Flask.
Home-page: https://github.com/snakeclub/HiveNetAssemble/HiveNetSimpleFlask
Author: 黎慧剑
Author-email: snakeclub@163.com
Maintainer: 黎慧剑
Maintainer-email: snakeclub@163.com
License: Mozilla Public License 2.0
Keywords: HiveNetAssemble HiveNetSimpleFlask flask development python lib
Platform: all
Classifier: Operating System :: OS Independent
Classifier: License :: OSI Approved :: Mozilla Public License 2.0 (MPL 2.0)
Classifier: Programming Language :: Python :: 3.6
Classifier: Topic :: Software Development :: Libraries
License-File: LICENSE
